{
    "indexPageTitle": "AEG սպասք լվացող մեքենաների վերանորոգում",
    "title": "AEG սպասք լվացող մեքենաների հաճախակի խափանումներ",
    "subTitle": "Չեք գտել ձեր խնդրի լուծո՞ւմը",
    "subSign": "Նշան",
    "subCauses": "Պատճառներ",
    "btnText": "Կանչել վարպետ",
    "parentURL": "/services/spasq-lvacoq-meqenaneri-veranorogum/aeg/",

    "items": [
        {
            "slug": "aeg-dishwasher-not-starting",
            "title": "AEG սպասք լվացող մեքենան չի գործարկվում",
            "sign": "Մեքենան չի արձագանքում մեկնարկի կոճակին կամ ծրագիրը չի սկսվում",
            "causes": "Խնդիր հոսանքի մատակարարման, դռան փականի կամ կառավարման մոդուլի հետ",
            "slugs": [
                "aeg-power-cord-damage",
                "aeg-door-lock-failure",
                "aeg-control-board-failure",
                "aeg-touch-panel-malfunction"
            ]
        },
        {
            "slug": "aeg-dishwasher-not-draining",
            "title": "AEG սպասք լվացող մեքենան չի հեռացնում ջուրը",
            "sign": "Ցիկլի ավարտից հետո խցիկում ջուր է մնում",
            "causes": "Ջրահեռացման համակարգի խցանում կամ ջրահեռացման պոմպի անսարքություն",
            "slugs": [
                "aeg-drain-pump-failure",
                "aeg-drain-hose-clog",
                "aeg-filter-blockage",
                "aeg-pressure-switch-error"
            ]
        },
        {
            "slug": "aeg-dishwasher-not-filling-with-water",
            "title": "AEG սպասք լվացող մեքենան ջուր չի լցնում",
            "sign": "Ցիկլը սկսվում է, բայց ջուրը չի մտնում խցիկ",
            "causes": "Մուտքային փականի կամ Aquastop համակարգի անսարքություն",
            "slugs": [
                "aeg-water-inlet-valve-failure",
                "aeg-aquastop-activation",
                "aeg-pressure-switch-error",
                "aeg-control-board-failure"
            ]
        },
        {
            "slug": "aeg-dishwasher-leaking-water",
            "title": "AEG սպասք լվացող մեքենան արտահոսում է",
            "sign": "Աշխատանքի ընթացքում մեքենայի տակ ջուր է հայտնվում",
            "causes": "Կնքիչների, խողովակների կամ ներքին միացումների վնասում",
            "slugs": [
                "aeg-door-seal-damage",
                "aeg-hose-connection-leak",
                "aeg-circulation-pump-leak",
                "aeg-leak-sensor-triggered"
            ]
        },
        {
            "slug": "aeg-dishwasher-not-heating-water",
            "title": "AEG սպասք լվացող մեքենան չի տաքացնում ջուրը",
            "sign": "Սպասքը մնում է սառը և վատ է լվացվում",
            "causes": "Տաքացուցիչի, թերմոստատի կամ ջերմաստիճանի տվիչի անսարքություն",
            "slugs": [
                "aeg-heating-element-failure",
                "aeg-ntc-sensor-failure",
                "aeg-thermostat-error",
                "aeg-control-board-failure"
            ]
        },
        {
            "slug": "aeg-dishwasher-not-drying",
            "title": "AEG սպասք լվացող մեքենան չի չորացնում սպասքը",
            "sign": "Ծրագրի ավարտից հետո սպասքը մնում է խոնավ",
            "causes": "Չորացման կամ օդափոխության համակարգի խափանում",
            "slugs": [
                "aeg-heating-element-failure",
                "aeg-drying-fan-failure",
                "aeg-ventilation-duct-blockage",
                "aeg-control-board-failure"
            ]
        },
        {
            "slug": "aeg-dishwasher-making-noise",
            "title": "AEG սպասք լվացող մեքենան աղմկում է աշխատանքի ընթացքում",
            "sign": "Լսվում են կողմնակի ձայներ, բզզոց կամ ճռռոց",
            "causes": "Պոմպի մաշվածություն կամ օտար առարկաների ներթափանցում",
            "slugs": [
                "aeg-circulation-pump-failure",
                "aeg-drain-pump-failure",
                "aeg-spray-arm-obstruction"
            ]
        },
        {
            "slug": "aeg-dishwasher-not-cleaning-properly",
            "title": "AEG սպասք լվացող մեքենան վատ է լվանում սպասքը",
            "sign": "Սպասքի վրա մնում են կեղտ և հետքեր",
            "causes": "Ջրի անբավարար ճնշում կամ ցողիչների խցանում",
            "slugs": [
                "aeg-spray-arm-clog",
                "aeg-circulation-pump-failure",
                "aeg-filter-blockage",
                "aeg-detergent-dispenser-failure"
            ]
        },
        {
            "slug": "aeg-dishwasher-error-code",
            "title": "AEG սպասք լվացող մեքենան ցույց է տալիս սխալ",
            "sign": "Էկրանին ցուցադրվում է անսարքության կոդ",
            "causes": "Տվիչների կամ էլեկտրոնային մոդուլի խափանում",
            "slugs": [
                "aeg-control-board-failure",
                "aeg-ntc-sensor-failure",
                "aeg-pressure-switch-error",
                "aeg-leak-sensor-triggered"
            ]
        },
        {
            "slug": "aeg-dishwasher-stops-mid-cycle",
            "title": "AEG սպասք լվացող մեքենան կանգ է առնում ցիկլի ընթացքում",
            "sign": "Ծրագիրը ընդհատվում է մինչև ավարտը",
            "causes": "Գերտաքացում, էլեկտրոնիկայի խափանում կամ ջրամատակարարման խնդիրներ",
            "slugs": [
                "aeg-heating-element-failure",
                "aeg-water-inlet-valve-failure",
                "aeg-control-board-failure"
            ]
        },
        {
            "slug": "aeg-dishwasher-door-not-closing",
            "title": "AEG սպասք լվացող մեքենայի դուռը չի փակվում",
            "sign": "Մեքենան չի գործարկվում չփակված դռան պատճառով",
            "causes": "Փականի անսարքություն կամ ծխնիների շեղում",
            "slugs": [
                "aeg-door-lock-failure",
                "aeg-door-hinge-damage",
                "aeg-door-sensor-error"
            ]
        },
        {
            "slug": "aeg-dishwasher-trips-breaker",
            "title": "AEG սպասք լվացող մեքենան անջատում է ավտոմատը",
            "sign": "Պաշտպանիչ ավտոմատը անջատում է հոսանքը գործարկման պահին",
            "causes": "Տաքացուցիչի, պոմպի կամ ցանցային ֆիլտրի կարճ միացում",
            "slugs": [
                "aeg-heating-element-short-circuit",
                "aeg-circulation-pump-short-circuit",
                "aeg-noise-filter-burnt",
                "aeg-control-board-failure"
            ]
        },

        {
            "slug": "aeg-power-cord-damage",
            "title": "AEG սնուցման մալուխի վնասում",
            "sign": "Մեկուսացման խախտումը կամ մալուխի լարերի ներքին խզումը հանգեցնում է կառավարման մոդուլին հոսանքի չմատակարարմանը։",
            "causes": "Մեքենան ամբողջությամբ չի միանում, ցուցադրություն չկա։",
            "slugs": []
        },
        {
            "slug": "aeg-door-lock-failure",
            "title": "AEG դռան փականի անսարքություն",
            "sign": "Արգելափակման մեխանիզմի մաշվածությունը կամ կոտրվելը թույլ չի տալիս համակարգին ֆիքսել դռան փակվելը։",
            "causes": "Ծրագիրը չի գործարկվում, ցուցադրվում է դռան սխալ։",
            "slugs": []
        },
        {
            "slug": "aeg-control-board-failure",
            "title": "AEG կառավարման մոդուլի խափանում",
            "sign": "Էլեկտրոնային պլատի վնասումը խաթարում է հանգույցների աշխատանքը և ծրագրերի կատարումը։",
            "causes": "Մեքենան կախվում է, չի արձագանքում հրամաններին կամ ինքնաբերաբար կանգ է առնում։",
            "slugs": []
        },
        {
            "slug": "aeg-touch-panel-malfunction",
            "title": "AEG սենսորային վահանակի անսարքություն",
            "sign": "Սենսորային վահանակը կորցնում է զգայունությունը կոնտակտների մաշվածության կամ ծրագրային խափանման պատճառով։",
            "causes": "Կոճակները չեն արձագանքում կամ գործում են սխալ։",
            "slugs": []
        },
        {
            "slug": "aeg-drain-pump-failure",
            "title": "AEG ջրահեռացման պոմպի անսարքություն",
            "sign": "Պոմպի շարժիչի կամ թիակի մաշվածությունը խոչընդոտում է ջրի հեռացումը ցիկլի ավարտից հետո։",
            "causes": "Ջուրը մնում է խցիկում լվացումից հետո։",
            "slugs": []
        },
        {
            "slug": "aeg-drain-hose-clog",
            "title": "AEG ջրահեռացման խողովակի խցանում",
            "sign": "Ջրահեռացման գծում կուտակված աղտոտումները արգելափակում են ջրի բնական արտահոսքը։",
            "causes": "Դանդաղ ջրահեռացում կամ դրա լիակատար բացակայություն։",
            "slugs": []
        },
        {
            "slug": "aeg-filter-blockage",
            "title": "AEG ֆիլտրի խցանում",
            "sign": "Ֆիլտրում սննդի մնացորդների կուտակումը նվազեցնում է համակարգի թողունակությունը։",
            "causes": "Վատ ջրահեռացում և տհաճ հոտ խցիկի ներսում։",
            "slugs": []
        },
        {
            "slug": "aeg-pressure-switch-error",
            "title": "AEG ջրի մակարդակի տվիչի սխալ",
            "sign": "Ջրի մակարդակի տվիչը փոխանցում է սխալ տվյալներ՝ խաթարելով ջրի լցման կամ հեռացման գործընթացը։",
            "causes": "Մեքենան ջուր չի լցնում կամ կանգ է առնում սխալով։",
            "slugs": []
        },
        {
            "slug": "aeg-water-inlet-valve-failure",
            "title": "AEG մուտքային փականի անսարքություն",
            "sign": "Էլեկտրամագնիսական փականը չի բացվում կամ աշխատում է անկայուն՝ խոչընդոտելով ջրի մուտքը։",
            "causes": "Ցիկլի սկզբում ջրի լցում չի կատարվում։",
            "slugs": []
        },
        {
            "slug": "aeg-aquastop-activation",
            "title": "AEG Aquastop համակարգի գործարկում",
            "sign": "Պաշտպանական համակարգը դադարեցնում է ջրի մատակարարումը կորպուսի ներսում արտահոսք հայտնաբերելիս։",
            "causes": "Մեքենան ջուր չի լցնում, հնարավոր է սխալի կոդ։",
            "slugs": []
        },
        {
            "slug": "aeg-door-seal-damage",
            "title": "AEG դռան կնքիչի վնասում",
            "sign": "Ռետինե կնքիչի մաշվածությունը կամ ձևափոխումը խախտում է խցիկի հերմետիկությունը։",
            "causes": "Աշխատանքի ընթացքում դռան տակից արտահոսք է առաջանում։",
            "slugs": []
        },
        {
            "slug": "aeg-hose-connection-leak",
            "title": "AEG խողովակների միացումների արտահոսք",
            "sign": "Թուլացած սեղմակները կամ միացումների ճաքերը առաջացնում են ջրի արտահոսք։",
            "causes": "Մեքենայի տակ ջուր է կուտակվում։",
            "slugs": []
        },
        {
            "slug": "aeg-circulation-pump-leak",
            "title": "AEG շրջանառության պոմպի արտահոսք",
            "sign": "Պոմպի կորպուսի կամ կնքիչների վնասումը հանգեցնում է սարքի ներսում ջրի արտահոսքի։",
            "causes": "Արտահոսքից պաշտպանության համակարգը գործարկվում է, մեքենան կանգ է առնում։",
            "slugs": []
        },
        {
            "slug": "aeg-leak-sensor-triggered",
            "title": "AEG արտահոսքի տվիչի գործարկում",
            "sign": "Տվիչը ֆիքսում է ջրի առկայությունը տակդիրում և արգելափակում հետագա աշխատանքը։",
            "causes": "Մեքենան չի սկսում նոր ցիկլ և ցուցադրում է սխալ։",
            "slugs": []
        },
        {
            "slug": "aeg-heating-element-failure",
            "title": "AEG տաքացուցիչի անսարքություն",
            "sign": "Տաքացուցիչը դադարում է ջուրը տաքացնել պարույրի այրման կամ շղթայի խզման պատճառով։",
            "causes": "Ջուրը մնում է սառը, լվացման որակը նվազում է։",
            "slugs": []
        },
        {
            "slug": "aeg-ntc-sensor-failure",
            "title": "AEG ջերմաստիճանի տվիչի անսարքություն",
            "sign": "NTC տվիչը փոխանցում է սխալ ջերմաստիճանային ցուցանիշներ՝ խաթարելով տաքացման գործընթացը։",
            "causes": "Ցիկլը կատարվում է առանց տաքացման կամ ավարտվում է սխալով։",
            "slugs": []
        },
        {
            "slug": "aeg-thermostat-error",
            "title": "AEG թերմոստատի անսարքություն",
            "sign": "Թերմոստատը սխալ է վերահսկում ջրի ջերմաստիճանը՝ առաջացնելով գերտաքացում կամ տաքացման բացակայություն։",
            "causes": "Ծրագիրը ընդհատվում է կամ ջուրը մնում է սառը։",
            "slugs": []
        },
        {
            "slug": "aeg-drying-fan-failure",
            "title": "AEG չորացման օդափոխիչի անսարքություն",
            "sign": "Օդափոխիչը դադարում է ապահովել տաք օդի շրջանառությունը խցիկի ներսում։",
            "causes": "Սպասքը մնում է խոնավ ծրագրի ավարտից հետո։",
            "slugs": []
        },
        {
            "slug": "aeg-ventilation-duct-blockage",
            "title": "AEG օդափոխության խողովակի խցանում",
            "sign": "Օդի շրջանառության խախտումը նվազեցնում է չորացման արդյունավետությունը։",
            "causes": "Սպասքի վրա մնում են ջրի կաթիլներ։",
            "slugs": []
        },
        {
            "slug": "aeg-circulation-pump-failure",
            "title": "AEG շրջանառության պոմպի անսարքություն",
            "sign": "Պոմպը չի ստեղծում անհրաժեշտ ճնշում՝ ջուրը ցողիչներին մատակարարելու համար։",
            "causes": "Սպասքը վատ է լվացվում, լսվում է կողմնակի աղմուկ։",
            "slugs": []
        },
        {
            "slug": "aeg-spray-arm-obstruction",
            "title": "AEG ցողիչի արգելափակում",
            "sign": "Ցողիչի անցքերը խցանվում են սննդի մնացորդներով՝ նվազեցնելով ջրի ճնշումը։",
            "causes": "Սպասքի վրա մնում են կեղտեր։",
            "slugs": []
        },
        {
            "slug": "aeg-spray-arm-clog",
            "title": "AEG ցողիչի վարդակների խցանում",
            "sign": "Վարդակների ներսում կուտակումները խոչընդոտում են ջրի հավասարաչափ բաշխմանը։",
            "causes": "Սպասքի անհավասար լվացում։",
            "slugs": []
        },
        {
            "slug": "aeg-detergent-dispenser-failure",
            "title": "AEG լվացող միջոցի դոզատորի անսարքություն",
            "sign": "Դոզատորի կափարիչի բացման մեխանիզմը չի գործարկվում ցիկլի ընթացքում։",
            "causes": "Լվացող միջոցը մնում է չլուծված։",
            "slugs": []
        },
        {
            "slug": "aeg-door-hinge-damage",
            "title": "AEG դռան ծխնիների վնասում",
            "sign": "Ծխնիների մաշվածությունը բերում է դռան շեղման և ճիշտ փակվելու անհնարինության։",
            "causes": "Դուռը փակվում է դժվարությամբ կամ չի ֆիքսվում։",
            "slugs": []
        },
        {
            "slug": "aeg-door-sensor-error",
            "title": "AEG դռան տվիչի սխալ",
            "sign": "Տվիչը չի ճանաչում դռան դիրքը նույնիսկ սերտ փակման դեպքում։",
            "causes": "Ծրագիրը չի գործարկվում։",
            "slugs": []
        },
        {
            "slug": "aeg-heating-element-short-circuit",
            "title": "AEG տաքացուցիչի կարճ միացում",
            "sign": "Տաքացուցիչի մեկուսացման վնասումը առաջացնում է հոսանքի արտահոսք և ցանցի գերբեռնվածություն։",
            "causes": "Տաքացման մեկնարկի ժամանակ անջատվում է ավտոմատը։",
            "slugs": []
        },
        {
            "slug": "aeg-circulation-pump-short-circuit",
            "title": "AEG պոմպի կարճ միացում",
            "sign": "Շարժիչի փաթաթման վնասումը հանգեցնում է կարճ միացման։",
            "causes": "Ծրագրի մեկնարկի ժամանակ անջատվում է ավտոմատը։",
            "slugs": []
        },
        {
            "slug": "aeg-noise-filter-burnt",
            "title": "AEG ցանցային ֆիլտրի այրում",
            "sign": "Ցանցային ֆիլտրը շարքից դուրս է գալիս լարման տատանումների դեպքում։",
            "causes": "Մեքենան չի միանում կամ անջատում է ավտոմատը։",
            "slugs": []
        }


    ]
}